setup.py
synolopy/__init__.py
synolopy/cgi.py
synolopy/devices.py
synolopy/errors.py
synolopy.egg-info/PKG-INFO
synolopy.egg-info/SOURCES.txt
synolopy.egg-info/dependency_links.txt
synolopy.egg-info/top_level.txt