Metadata-Version: 1.1
Name: synolopy
Version: 0.1.2
Summary: Synology Python API
Home-page: UNKNOWN
Author: Thibaut Havel
Author-email: UNKNOWN
License: UNKNOWN
Platform: UNKNOWN
Requires: requests
